pytest_airflow/__init__.py
pytest_airflow/_version.py
pytest_airflow/operators.py
pytest_airflow/plugin.py
pytest_airflow-0.0.3.dist-info/LICENSE
pytest_airflow-0.0.3.dist-info/METADATA
pytest_airflow-0.0.3.dist-info/WHEEL
pytest_airflow-0.0.3.dist-info/entry_points.txt
pytest_airflow-0.0.3.dist-info/top_level.txt
pytest_airflow-0.0.3.dist-info/RECORD
