Metadata-Version: 2.1
Name: pytest-airflow
Version: 0.0.3
Summary: pytest support for airflow.
Home-page: https://github.com/Flowminder/pytest-airflow
Author: Guilherme Zagatti
Author-email: guilherme.zagatti@flowminder.org
License: UNKNOWN
Platform: UNKNOWN
Classifier: Framework :: Pytest
Classifier: Development Status :: 3 - Alpha
Classifier: License :: OSI Approved :: Mozilla Public License 2.0 (MPL 2.0)
Classifier: Programming Language :: Python :: 3.5
Classifier: Programming Language :: Python :: 3.6
Classifier: Programming Language :: Python :: 3.7
Classifier: Natural Language :: English
Requires-Python: >=3.5
Requires-Dist: pytest (>=4.4.0)
Requires-Dist: apache-airflow (>=1.8.0)
